gladeparser/__init__.py
gladeparser/columns.py
gladeparser/constants.py
gladeparser/expressions.py
gladeparser/filters.py
gladeparser/parser.py
gladeparser/utils.py
gladeparser/backends/__init__.py
gladeparser/backends/dataframe.py
gladeparser/backends/hdf5.py
gladeparser/backends/pandas.py
gladeparser/backends/polars.py
gladeparser-0.2.0.dist-info/LICENSE
gladeparser-0.2.0.dist-info/METADATA
gladeparser-0.2.0.dist-info/WHEEL
gladeparser-0.2.0.dist-info/top_level.txt
gladeparser-0.2.0.dist-info/RECORD
