Metadata-Version: 2.1
Name: gladeparser
Version: 0.2.0
Summary: Parser for the GLADE+ catalog.
Author-email: Bernardo Veronese <bernardo.veronese@edu.ufes.br>
License: MIT License
Project-URL: Homepage, https://github.com/binado/gladeparser
Keywords: gravitational waves,galaxy catalog,cosmology
Classifier: Programming Language :: Python :: 3
Requires-Python: >=3.8
License-File: LICENSE
Requires-Dist: numpy <2.0
Requires-Dist: polars
Requires-Dist: pandas
Requires-Dist: tables
Requires-Dist: tqdm
Provides-Extra: ci
Requires-Dist: pytest ; extra == 'ci'
Provides-Extra: dev
Requires-Dist: pytest ; extra == 'dev'
Requires-Dist: ruff ; extra == 'dev'
Requires-Dist: pre-commit ; extra == 'dev'
